Metadata-Version: 1.1
Name: pyicane
Version: 0.1.2
Summary: Python wrapper for ICANE Statistical Data and Metadata API
Home-page: https://github.com/predicador37/pyicane
Author: Miguel Expósito Martín
Author-email: miguel.exposito@gmail.com
License: Apache License 2.0
Keywords: restful,json,statistics,dataframe,wrapper
Platform: UNKNOWN
Classifier: Development Status :: 4 - Beta
Classifier: Environment :: Console
Classifier: Intended Audience :: Developers
Classifier: Intended Audience :: Science/Research
Classifier: License :: OSI Approved :: Apache Software License
Classifier: Operating System :: MacOS :: MacOS X
Classifier: Operating System :: Microsoft :: Windows
Classifier: Operating System :: POSIX
Classifier: Programming Language :: Python
Classifier: Topic :: Scientific/Engineering :: Information Analysis
Classifier: Topic :: Software Development :: Libraries
